[
  {
    "season": "0",
    "episode": "1",
    "tvdb url": "https://www.thetvdb.com/dereferrer/episode/4606576",
    "myanimelist url": "https://myanimelist.net/anime/16614",
    "anidb": null,
    "anilist": 16614,
    "animenewsnetwork": null,
    "animeplanet": "busou-shinki-ova",
    "anisearch": 4906,
    "annict": null,
    "imdb": null,
    "kaize": "busou-shinki-install-x-dream",
    "kaize_id": 1218,
    "kitsu": 7475,
    "livechart": 2738,
    "myanimelist": 16614,
    "nautiljon": null,
    "nautiljon_id": null,
    "notify": "VNjKtKmmg",
    "otakotaku": null,
    "shikimori": 16614,
    "shoboi": null,
    "silveryasha": 2257,
    "simkl": null,
    "themoviedb": null,
    "thetvdb": "4606576",
    "title": "Busou Shinki: Install x Dream",
    "trakt": null,
    "trakt_season": null,
    "trakt_type": null
  }
]