[
    {
        "season": "2",
        "tvdb url": "https://www.thetvdb.com/dereferrer/season/499995",
        "myanimelist url": "https://myanimelist.net/anime/14645",
        "anidb": 9284,
        "anilist": 14645,
        "animenewsnetwork": 14733,
        "animeplanet": "hiiro-no-kakera-the-tamayori-princess-saga-2",
        "anisearch": 7923,
        "annict": 1822,
        "imdb": null,
        "kaize": null,
        "kaize_id": null,
        "kitsu": 7146,
        "livechart": 942,
        "myanimelist": 14645,
        "nautiljon": null,
        "nautiljon_id": null,
        "notify": "T1OOtFimg",
        "otakotaku": null,
        "shikimori": 14645,
        "shoboi": 2734,
        "silveryasha": null,
        "simkl": 40338,
        "themoviedb": null,
        "thetvdb": "499995",
        "title": "Hiiro no Kakera 2nd Season",
        "trakt": 44757,
        "trakt_season": 2,
        "trakt_type": "shows"
    }
]