[
    {
        "season": 0,
        "episode": 2,
        "thetvdb url": "https://www.thetvdb.com/dereferrer/episode/6009250",
        "myanimelist url": "https://myanimelist.net/anime/35145/Kobayashi-san_Chi_no_OO_Dragon/episode/1",
        "myanimelist": 35145,
        "thetvdb": 6009250
    },
    {
        "season": 0,
        "episode": 6,
        "thetvdb url": "https://www.thetvdb.com/dereferrer/episode/6208348",
        "myanimelist url": "https://myanimelist.net/anime/35145/Kobayashi-san_Chi_no_OO_Dragon/episode/2",
        "myanimelist": 35145,
        "thetvdb": 6208348
    },
    {
        "season": 0,
        "episode": 8,
        "thetvdb url": "https://www.thetvdb.com/dereferrer/episode/6276274",
        "myanimelist url": "https://myanimelist.net/anime/35145/Kobayashi-san_Chi_no_OO_Dragon/episode/3",
        "myanimelist": 35145,
        "thetvdb": 6276274
    }
]