[
    {
        "season": "0",
        "episode": "4",
        "tvdb url": "https://www.thetvdb.com/dereferrer/episode/7324082",
        "myanimelist url": "https://myanimelist.net/anime/40080",
        "anidb": 15035,
        "anilist": 108981,
        "animenewsnetwork": null,
        "animeplanet": "quanzhi-gaoshou-movie-for-the-glory",
        "anisearch": 14775,
        "annict": 10883,
        "imdb": null,
        "kaize": "quanzhi-gaoshou-dianfeng-rongyao",
        "kaize_id": 5594,
        "kitsu": 42673,
        "livechart": 9454,
        "myanimelist": 40080,
        "nautiljon": "quan+zhi+gao+shou+zhi+dian+feng+rong+yao",
        "nautiljon_id": 8677,
        "notify": "DRlvzKkMg",
        "otakotaku": null,
        "shikimori": 40080,
        "shoboi": null,
        "silveryasha": 1205,
        "simkl": 1202097,
        "themoviedb": null,
        "thetvdb": "7324082",
        "title": "Quanzhi Gaoshou: Dianfeng Rongyao",
        "trakt": 456794,
        "trakt_season": null,
        "trakt_type": "movies"
    }
]