[
    {
        "season": "1",
        "thetvdb url": "https://www.thetvdb.com/dereferrer/season/17630",
        "myanimelist url": "https://myanimelist.net/anime/476",
        "myanimelist": 476,
        "thetvdb": 17630
    },
    {
        "season": 1,
        "episode": 1,
        "thetvdb url": "https://www.thetvdb.com/dereferrer/episode/327836",
        "myanimelist url": "https://myanimelist.net/anime/476/Ginban_Kaleidoscope/episode/1",
        "myanimelist": 476,
        "thetvdb": 327836
    },
    {
        "season": 1,
        "episode": 2,
        "thetvdb url": "https://www.thetvdb.com/dereferrer/episode/327837",
        "myanimelist url": "https://myanimelist.net/anime/476/Ginban_Kaleidoscope/episode/2",
        "myanimelist": 476,
        "thetvdb": 327837
    },
    {
        "season": 1,
        "episode": 3,
        "thetvdb url": "https://www.thetvdb.com/dereferrer/episode/327838",
        "myanimelist url": "https://myanimelist.net/anime/476/Ginban_Kaleidoscope/episode/3",
        "myanimelist": 476,
        "thetvdb": 327838
    },
    {
        "season": 1,
        "episode": 4,
        "thetvdb url": "https://www.thetvdb.com/dereferrer/episode/327839",
        "myanimelist url": "https://myanimelist.net/anime/476/Ginban_Kaleidoscope/episode/4",
        "myanimelist": 476,
        "thetvdb": 327839
    },
    {
        "season": 1,
        "episode": 5,
        "thetvdb url": "https://www.thetvdb.com/dereferrer/episode/327840",
        "myanimelist url": "https://myanimelist.net/anime/476/Ginban_Kaleidoscope/episode/5",
        "myanimelist": 476,
        "thetvdb": 327840
    },
    {
        "season": 1,
        "episode": 6,
        "thetvdb url": "https://www.thetvdb.com/dereferrer/episode/327841",
        "myanimelist url": "https://myanimelist.net/anime/476/Ginban_Kaleidoscope/episode/6",
        "myanimelist": 476,
        "thetvdb": 327841
    },
    {
        "season": 1,
        "episode": 7,
        "thetvdb url": "https://www.thetvdb.com/dereferrer/episode/327842",
        "myanimelist url": "https://myanimelist.net/anime/476/Ginban_Kaleidoscope/episode/7",
        "myanimelist": 476,
        "thetvdb": 327842
    },
    {
        "season": 1,
        "episode": 8,
        "thetvdb url": "https://www.thetvdb.com/dereferrer/episode/327843",
        "myanimelist url": "https://myanimelist.net/anime/476/Ginban_Kaleidoscope/episode/8",
        "myanimelist": 476,
        "thetvdb": 327843
    },
    {
        "season": 1,
        "episode": 9,
        "thetvdb url": "https://www.thetvdb.com/dereferrer/episode/327844",
        "myanimelist url": "https://myanimelist.net/anime/476/Ginban_Kaleidoscope/episode/9",
        "myanimelist": 476,
        "thetvdb": 327844
    },
    {
        "season": 1,
        "episode": 10,
        "thetvdb url": "https://www.thetvdb.com/dereferrer/episode/327845",
        "myanimelist url": "https://myanimelist.net/anime/476/Ginban_Kaleidoscope/episode/10",
        "myanimelist": 476,
        "thetvdb": 327845
    },
    {
        "season": 1,
        "episode": 11,
        "thetvdb url": "https://www.thetvdb.com/dereferrer/episode/327846",
        "myanimelist url": "https://myanimelist.net/anime/476/Ginban_Kaleidoscope/episode/11",
        "myanimelist": 476,
        "thetvdb": 327846
    },
    {
        "season": 1,
        "episode": 12,
        "thetvdb url": "https://www.thetvdb.com/dereferrer/episode/327847",
        "myanimelist url": "https://myanimelist.net/anime/476/Ginban_Kaleidoscope/episode/12",
        "myanimelist": 476,
        "thetvdb": 327847
    }
]