[
    {
        "thetvdb url": "https://www.thetvdb.com/dereferrer/series/263486",
        "myanimelist url": "https://myanimelist.net/anime/4935",
        "myanimelist": 4935,
        "thetvdb": 263486
    },
    {
        "season": "1",
        "thetvdb url": "https://www.thetvdb.com/dereferrer/season/503723",
        "myanimelist url": "https://myanimelist.net/anime/4935",
        "myanimelist": 4935,
        "thetvdb": 503723
    },
    {
        "season": 1,
        "episode": 1,
        "thetvdb url": "https://www.thetvdb.com/dereferrer/episode/4422830",
        "myanimelist url": "https://myanimelist.net/anime/4935/Ikkyuu-san/episode/1",
        "myanimelist": 4935,
        "thetvdb": 4422830
    },
    {
        "season": 1,
        "episode": 2,
        "thetvdb url": "https://www.thetvdb.com/dereferrer/episode/4422831",
        "myanimelist url": "https://myanimelist.net/anime/4935/Ikkyuu-san/episode/2",
        "myanimelist": 4935,
        "thetvdb": 4422831
    },
    {
        "season": 1,
        "episode": 3,
        "thetvdb url": "https://www.thetvdb.com/dereferrer/episode/4422832",
        "myanimelist url": "https://myanimelist.net/anime/4935/Ikkyuu-san/episode/3",
        "myanimelist": 4935,
        "thetvdb": 4422832
    },
    {
        "season": 1,
        "episode": 4,
        "thetvdb url": "https://www.thetvdb.com/dereferrer/episode/4422835",
        "myanimelist url": "https://myanimelist.net/anime/4935/Ikkyuu-san/episode/4",
        "myanimelist": 4935,
        "thetvdb": 4422835
    },
    {
        "season": 1,
        "episode": 5,
        "thetvdb url": "https://www.thetvdb.com/dereferrer/episode/4422836",
        "myanimelist url": "https://myanimelist.net/anime/4935/Ikkyuu-san/episode/5",
        "myanimelist": 4935,
        "thetvdb": 4422836
    },
    {
        "season": 1,
        "episode": 6,
        "thetvdb url": "https://www.thetvdb.com/dereferrer/episode/4422837",
        "myanimelist url": "https://myanimelist.net/anime/4935/Ikkyuu-san/episode/6",
        "myanimelist": 4935,
        "thetvdb": 4422837
    },
    {
        "season": 1,
        "episode": 7,
        "thetvdb url": "https://www.thetvdb.com/dereferrer/episode/4422838",
        "myanimelist url": "https://myanimelist.net/anime/4935/Ikkyuu-san/episode/7",
        "myanimelist": 4935,
        "thetvdb": 4422838
    },
    {
        "season": 1,
        "episode": 8,
        "thetvdb url": "https://www.thetvdb.com/dereferrer/episode/4422839",
        "myanimelist url": "https://myanimelist.net/anime/4935/Ikkyuu-san/episode/8",
        "myanimelist": 4935,
        "thetvdb": 4422839
    },
    {
        "season": 1,
        "episode": 9,
        "thetvdb url": "https://www.thetvdb.com/dereferrer/episode/4422840",
        "myanimelist url": "https://myanimelist.net/anime/4935/Ikkyuu-san/episode/9",
        "myanimelist": 4935,
        "thetvdb": 4422840
    },
    {
        "season": 1,
        "episode": 10,
        "thetvdb url": "https://www.thetvdb.com/dereferrer/episode/4422841",
        "myanimelist url": "https://myanimelist.net/anime/4935/Ikkyuu-san/episode/10",
        "myanimelist": 4935,
        "thetvdb": 4422841
    },
    {
        "season": 1,
        "episode": 11,
        "thetvdb url": "https://www.thetvdb.com/dereferrer/episode/4422842",
        "myanimelist url": "https://myanimelist.net/anime/4935/Ikkyuu-san/episode/11",
        "myanimelist": 4935,
        "thetvdb": 4422842
    },
    {
        "season": 1,
        "episode": 12,
        "thetvdb url": "https://www.thetvdb.com/dereferrer/episode/4422843",
        "myanimelist url": "https://myanimelist.net/anime/4935/Ikkyuu-san/episode/12",
        "myanimelist": 4935,
        "thetvdb": 4422843
    },
    {
        "season": 1,
        "episode": 13,
        "thetvdb url": "https://www.thetvdb.com/dereferrer/episode/4422845",
        "myanimelist url": "https://myanimelist.net/anime/4935/Ikkyuu-san/episode/13",
        "myanimelist": 4935,
        "thetvdb": 4422845
    },
    {
        "season": "2",
        "thetvdb url": "https://www.thetvdb.com/dereferrer/season/503725",
        "myanimelist url": "https://myanimelist.net/anime/4935",
        "myanimelist": 4935,
        "thetvdb": 503725
    },
    {
        "season": 2,
        "episode": 1,
        "thetvdb url": "https://www.thetvdb.com/dereferrer/episode/4422846",
        "myanimelist url": "https://myanimelist.net/anime/4935/Ikkyuu-san/episode/14",
        "myanimelist": 4935,
        "thetvdb": 4422846
    },
    {
        "season": 2,
        "episode": 2,
        "thetvdb url": "https://www.thetvdb.com/dereferrer/episode/4422848",
        "myanimelist url": "https://myanimelist.net/anime/4935/Ikkyuu-san/episode/15",
        "myanimelist": 4935,
        "thetvdb": 4422848
    },
    {
        "season": 2,
        "episode": 3,
        "thetvdb url": "https://www.thetvdb.com/dereferrer/episode/4422849",
        "myanimelist url": "https://myanimelist.net/anime/4935/Ikkyuu-san/episode/16",
        "myanimelist": 4935,
        "thetvdb": 4422849
    },
    {
        "season": 2,
        "episode": 4,
        "thetvdb url": "https://www.thetvdb.com/dereferrer/episode/4422850",
        "myanimelist url": "https://myanimelist.net/anime/4935/Ikkyuu-san/episode/17",
        "myanimelist": 4935,
        "thetvdb": 4422850
    },
    {
        "season": 2,
        "episode": 5,
        "thetvdb url": "https://www.thetvdb.com/dereferrer/episode/4422851",
        "myanimelist url": "https://myanimelist.net/anime/4935/Ikkyuu-san/episode/18",
        "myanimelist": 4935,
        "thetvdb": 4422851
    },
    {
        "season": 2,
        "episode": 6,
        "thetvdb url": "https://www.thetvdb.com/dereferrer/episode/4422852",
        "myanimelist url": "https://myanimelist.net/anime/4935/Ikkyuu-san/episode/19",
        "myanimelist": 4935,
        "thetvdb": 4422852
    },
    {
        "season": 2,
        "episode": 7,
        "thetvdb url": "https://www.thetvdb.com/dereferrer/episode/4422853",
        "myanimelist url": "https://myanimelist.net/anime/4935/Ikkyuu-san/episode/20",
        "myanimelist": 4935,
        "thetvdb": 4422853
    },
    {
        "season": 2,
        "episode": 8,
        "thetvdb url": "https://www.thetvdb.com/dereferrer/episode/4422854",
        "myanimelist url": "https://myanimelist.net/anime/4935/Ikkyuu-san/episode/21",
        "myanimelist": 4935,
        "thetvdb": 4422854
    },
    {
        "season": 2,
        "episode": 9,
        "thetvdb url": "https://www.thetvdb.com/dereferrer/episode/4422855",
        "myanimelist url": "https://myanimelist.net/anime/4935/Ikkyuu-san/episode/22",
        "myanimelist": 4935,
        "thetvdb": 4422855
    },
    {
        "season": 2,
        "episode": 10,
        "thetvdb url": "https://www.thetvdb.com/dereferrer/episode/4422856",
        "myanimelist url": "https://myanimelist.net/anime/4935/Ikkyuu-san/episode/23",
        "myanimelist": 4935,
        "thetvdb": 4422856
    },
    {
        "season": 2,
        "episode": 11,
        "thetvdb url": "https://www.thetvdb.com/dereferrer/episode/4422857",
        "myanimelist url": "https://myanimelist.net/anime/4935/Ikkyuu-san/episode/24",
        "myanimelist": 4935,
        "thetvdb": 4422857
    },
    {
        "season": 2,
        "episode": 12,
        "thetvdb url": "https://www.thetvdb.com/dereferrer/episode/4422858",
        "myanimelist url": "https://myanimelist.net/anime/4935/Ikkyuu-san/episode/25",
        "myanimelist": 4935,
        "thetvdb": 4422858
    },
    {
        "season": 2,
        "episode": 13,
        "thetvdb url": "https://www.thetvdb.com/dereferrer/episode/4422859",
        "myanimelist url": "https://myanimelist.net/anime/4935/Ikkyuu-san/episode/26",
        "myanimelist": 4935,
        "thetvdb": 4422859
    },
    {
        "season": "3",
        "thetvdb url": "https://www.thetvdb.com/dereferrer/season/503726",
        "myanimelist url": "https://myanimelist.net/anime/4935",
        "myanimelist": 4935,
        "thetvdb": 503726
    },
    {
        "season": 3,
        "episode": 1,
        "thetvdb url": "https://www.thetvdb.com/dereferrer/episode/4422860",
        "myanimelist url": "https://myanimelist.net/anime/4935/Ikkyuu-san/episode/27",
        "myanimelist": 4935,
        "thetvdb": 4422860
    },
    {
        "season": 3,
        "episode": 2,
        "thetvdb url": "https://www.thetvdb.com/dereferrer/episode/4422861",
        "myanimelist url": "https://myanimelist.net/anime/4935/Ikkyuu-san/episode/28",
        "myanimelist": 4935,
        "thetvdb": 4422861
    },
    {
        "season": 3,
        "episode": 3,
        "thetvdb url": "https://www.thetvdb.com/dereferrer/episode/4422862",
        "myanimelist url": "https://myanimelist.net/anime/4935/Ikkyuu-san/episode/29",
        "myanimelist": 4935,
        "thetvdb": 4422862
    },
    {
        "season": 3,
        "episode": 4,
        "thetvdb url": "https://www.thetvdb.com/dereferrer/episode/4422863",
        "myanimelist url": "https://myanimelist.net/anime/4935/Ikkyuu-san/episode/30",
        "myanimelist": 4935,
        "thetvdb": 4422863
    },
    {
        "season": 3,
        "episode": 5,
        "thetvdb url": "https://www.thetvdb.com/dereferrer/episode/4422864",
        "myanimelist url": "https://myanimelist.net/anime/4935/Ikkyuu-san/episode/31",
        "myanimelist": 4935,
        "thetvdb": 4422864
    },
    {
        "season": 3,
        "episode": 6,
        "thetvdb url": "https://www.thetvdb.com/dereferrer/episode/4422865",
        "myanimelist url": "https://myanimelist.net/anime/4935/Ikkyuu-san/episode/32",
        "myanimelist": 4935,
        "thetvdb": 4422865
    },
    {
        "season": 3,
        "episode": 7,
        "thetvdb url": "https://www.thetvdb.com/dereferrer/episode/4422866",
        "myanimelist url": "https://myanimelist.net/anime/4935/Ikkyuu-san/episode/33",
        "myanimelist": 4935,
        "thetvdb": 4422866
    },
    {
        "season": 3,
        "episode": 8,
        "thetvdb url": "https://www.thetvdb.com/dereferrer/episode/4422867",
        "myanimelist url": "https://myanimelist.net/anime/4935/Ikkyuu-san/episode/34",
        "myanimelist": 4935,
        "thetvdb": 4422867
    },
    {
        "season": 3,
        "episode": 9,
        "thetvdb url": "https://www.thetvdb.com/dereferrer/episode/4422868",
        "myanimelist url": "https://myanimelist.net/anime/4935/Ikkyuu-san/episode/35",
        "myanimelist": 4935,
        "thetvdb": 4422868
    },
    {
        "season": 3,
        "episode": 10,
        "thetvdb url": "https://www.thetvdb.com/dereferrer/episode/4422869",
        "myanimelist url": "https://myanimelist.net/anime/4935/Ikkyuu-san/episode/36",
        "myanimelist": 4935,
        "thetvdb": 4422869
    },
    {
        "season": 3,
        "episode": 11,
        "thetvdb url": "https://www.thetvdb.com/dereferrer/episode/4422870",
        "myanimelist url": "https://myanimelist.net/anime/4935/Ikkyuu-san/episode/37",
        "myanimelist": 4935,
        "thetvdb": 4422870
    },
    {
        "season": 3,
        "episode": 12,
        "thetvdb url": "https://www.thetvdb.com/dereferrer/episode/4422871",
        "myanimelist url": "https://myanimelist.net/anime/4935/Ikkyuu-san/episode/38",
        "myanimelist": 4935,
        "thetvdb": 4422871
    },
    {
        "season": 3,
        "episode": 13,
        "thetvdb url": "https://www.thetvdb.com/dereferrer/episode/4422872",
        "myanimelist url": "https://myanimelist.net/anime/4935/Ikkyuu-san/episode/39",
        "myanimelist": 4935,
        "thetvdb": 4422872
    },
    {
        "season": "4",
        "thetvdb url": "https://www.thetvdb.com/dereferrer/season/503727",
        "myanimelist url": "https://myanimelist.net/anime/4935",
        "myanimelist": 4935,
        "thetvdb": 503727
    },
    {
        "season": 4,
        "episode": 1,
        "thetvdb url": "https://www.thetvdb.com/dereferrer/episode/4422873",
        "myanimelist url": "https://myanimelist.net/anime/4935/Ikkyuu-san/episode/40",
        "myanimelist": 4935,
        "thetvdb": 4422873
    },
    {
        "season": 4,
        "episode": 2,
        "thetvdb url": "https://www.thetvdb.com/dereferrer/episode/4422875",
        "myanimelist url": "https://myanimelist.net/anime/4935/Ikkyuu-san/episode/41",
        "myanimelist": 4935,
        "thetvdb": 4422875
    },
    {
        "season": 4,
        "episode": 3,
        "thetvdb url": "https://www.thetvdb.com/dereferrer/episode/4422876",
        "myanimelist url": "https://myanimelist.net/anime/4935/Ikkyuu-san/episode/42",
        "myanimelist": 4935,
        "thetvdb": 4422876
    },
    {
        "season": 4,
        "episode": 4,
        "thetvdb url": "https://www.thetvdb.com/dereferrer/episode/4422877",
        "myanimelist url": "https://myanimelist.net/anime/4935/Ikkyuu-san/episode/43",
        "myanimelist": 4935,
        "thetvdb": 4422877
    },
    {
        "season": 4,
        "episode": 5,
        "thetvdb url": "https://www.thetvdb.com/dereferrer/episode/4422878",
        "myanimelist url": "https://myanimelist.net/anime/4935/Ikkyuu-san/episode/44",
        "myanimelist": 4935,
        "thetvdb": 4422878
    },
    {
        "season": 4,
        "episode": 6,
        "thetvdb url": "https://www.thetvdb.com/dereferrer/episode/4422879",
        "myanimelist url": "https://myanimelist.net/anime/4935/Ikkyuu-san/episode/45",
        "myanimelist": 4935,
        "thetvdb": 4422879
    },
    {
        "season": 4,
        "episode": 7,
        "thetvdb url": "https://www.thetvdb.com/dereferrer/episode/4422880",
        "myanimelist url": "https://myanimelist.net/anime/4935/Ikkyuu-san/episode/46",
        "myanimelist": 4935,
        "thetvdb": 4422880
    },
    {
        "season": 4,
        "episode": 8,
        "thetvdb url": "https://www.thetvdb.com/dereferrer/episode/4422881",
        "myanimelist url": "https://myanimelist.net/anime/4935/Ikkyuu-san/episode/47",
        "myanimelist": 4935,
        "thetvdb": 4422881
    },
    {
        "season": 4,
        "episode": 9,
        "thetvdb url": "https://www.thetvdb.com/dereferrer/episode/4422882",
        "myanimelist url": "https://myanimelist.net/anime/4935/Ikkyuu-san/episode/48",
        "myanimelist": 4935,
        "thetvdb": 4422882
    },
    {
        "season": 4,
        "episode": 10,
        "thetvdb url": "https://www.thetvdb.com/dereferrer/episode/4422883",
        "myanimelist url": "https://myanimelist.net/anime/4935/Ikkyuu-san/episode/49",
        "myanimelist": 4935,
        "thetvdb": 4422883
    },
    {
        "season": 4,
        "episode": 11,
        "thetvdb url": "https://www.thetvdb.com/dereferrer/episode/4422884",
        "myanimelist url": "https://myanimelist.net/anime/4935/Ikkyuu-san/episode/50",
        "myanimelist": 4935,
        "thetvdb": 4422884
    },
    {
        "season": 4,
        "episode": 12,
        "thetvdb url": "https://www.thetvdb.com/dereferrer/episode/4422885",
        "myanimelist url": "https://myanimelist.net/anime/4935/Ikkyuu-san/episode/51",
        "myanimelist": 4935,
        "thetvdb": 4422885
    },
    {
        "season": 4,
        "episode": 13,
        "thetvdb url": "https://www.thetvdb.com/dereferrer/episode/4422886",
        "myanimelist url": "https://myanimelist.net/anime/4935/Ikkyuu-san/episode/52",
        "myanimelist": 4935,
        "thetvdb": 4422886
    },
    {
        "season": "5",
        "thetvdb url": "https://www.thetvdb.com/dereferrer/season/1853572",
        "myanimelist url": "https://myanimelist.net/anime/4935",
        "myanimelist": 4935,
        "thetvdb": 1853572
    },
    {
        "season": 5,
        "episode": 1,
        "thetvdb url": "https://www.thetvdb.com/dereferrer/episode/7826738",
        "myanimelist url": "https://myanimelist.net/anime/4935/Ikkyuu-san/episode/53",
        "myanimelist": 4935,
        "thetvdb": 7826738
    },
    {
        "season": 5,
        "episode": 2,
        "thetvdb url": "https://www.thetvdb.com/dereferrer/episode/7826740",
        "myanimelist url": "https://myanimelist.net/anime/4935/Ikkyuu-san/episode/54",
        "myanimelist": 4935,
        "thetvdb": 7826740
    },
    {
        "season": 5,
        "episode": 3,
        "thetvdb url": "https://www.thetvdb.com/dereferrer/episode/7826745",
        "myanimelist url": "https://myanimelist.net/anime/4935/Ikkyuu-san/episode/55",
        "myanimelist": 4935,
        "thetvdb": 7826745
    },
    {
        "season": 5,
        "episode": 4,
        "thetvdb url": "https://www.thetvdb.com/dereferrer/episode/7826779",
        "myanimelist url": "https://myanimelist.net/anime/4935/Ikkyuu-san/episode/56",
        "myanimelist": 4935,
        "thetvdb": 7826779
    },
    {
        "season": 5,
        "episode": 5,
        "thetvdb url": "https://www.thetvdb.com/dereferrer/episode/7826782",
        "myanimelist url": "https://myanimelist.net/anime/4935/Ikkyuu-san/episode/57",
        "myanimelist": 4935,
        "thetvdb": 7826782
    },
    {
        "season": 5,
        "episode": 6,
        "thetvdb url": "https://www.thetvdb.com/dereferrer/episode/7826785",
        "myanimelist url": "https://myanimelist.net/anime/4935/Ikkyuu-san/episode/58",
        "myanimelist": 4935,
        "thetvdb": 7826785
    },
    {
        "season": 5,
        "episode": 7,
        "thetvdb url": "https://www.thetvdb.com/dereferrer/episode/7826787",
        "myanimelist url": "https://myanimelist.net/anime/4935/Ikkyuu-san/episode/59",
        "myanimelist": 4935,
        "thetvdb": 7826787
    },
    {
        "season": 5,
        "episode": 8,
        "thetvdb url": "https://www.thetvdb.com/dereferrer/episode/7826788",
        "myanimelist url": "https://myanimelist.net/anime/4935/Ikkyuu-san/episode/60",
        "myanimelist": 4935,
        "thetvdb": 7826788
    },
    {
        "season": 5,
        "episode": 9,
        "thetvdb url": "https://www.thetvdb.com/dereferrer/episode/7826789",
        "myanimelist url": "https://myanimelist.net/anime/4935/Ikkyuu-san/episode/61",
        "myanimelist": 4935,
        "thetvdb": 7826789
    },
    {
        "season": 5,
        "episode": 10,
        "thetvdb url": "https://www.thetvdb.com/dereferrer/episode/7826793",
        "myanimelist url": "https://myanimelist.net/anime/4935/Ikkyuu-san/episode/62",
        "myanimelist": 4935,
        "thetvdb": 7826793
    },
    {
        "season": 5,
        "episode": 11,
        "thetvdb url": "https://www.thetvdb.com/dereferrer/episode/7826797",
        "myanimelist url": "https://myanimelist.net/anime/4935/Ikkyuu-san/episode/63",
        "myanimelist": 4935,
        "thetvdb": 7826797
    },
    {
        "season": 5,
        "episode": 12,
        "thetvdb url": "https://www.thetvdb.com/dereferrer/episode/7826799",
        "myanimelist url": "https://myanimelist.net/anime/4935/Ikkyuu-san/episode/64",
        "myanimelist": 4935,
        "thetvdb": 7826799
    },
    {
        "season": 5,
        "episode": 13,
        "thetvdb url": "https://www.thetvdb.com/dereferrer/episode/7826802",
        "myanimelist url": "https://myanimelist.net/anime/4935/Ikkyuu-san/episode/65",
        "myanimelist": 4935,
        "thetvdb": 7826802
    },
    {
        "season": 5,
        "episode": 14,
        "thetvdb url": "https://www.thetvdb.com/dereferrer/episode/7826805",
        "myanimelist url": "https://myanimelist.net/anime/4935/Ikkyuu-san/episode/66",
        "myanimelist": 4935,
        "thetvdb": 7826805
    },
    {
        "season": 5,
        "episode": 15,
        "thetvdb url": "https://www.thetvdb.com/dereferrer/episode/7826809",
        "myanimelist url": "https://myanimelist.net/anime/4935/Ikkyuu-san/episode/67",
        "myanimelist": 4935,
        "thetvdb": 7826809
    },
    {
        "season": 5,
        "episode": 16,
        "thetvdb url": "https://www.thetvdb.com/dereferrer/episode/7826813",
        "myanimelist url": "https://myanimelist.net/anime/4935/Ikkyuu-san/episode/68",
        "myanimelist": 4935,
        "thetvdb": 7826813
    },
    {
        "season": 5,
        "episode": 17,
        "thetvdb url": "https://www.thetvdb.com/dereferrer/episode/7826814",
        "myanimelist url": "https://myanimelist.net/anime/4935/Ikkyuu-san/episode/69",
        "myanimelist": 4935,
        "thetvdb": 7826814
    },
    {
        "season": 5,
        "episode": 18,
        "thetvdb url": "https://www.thetvdb.com/dereferrer/episode/7826815",
        "myanimelist url": "https://myanimelist.net/anime/4935/Ikkyuu-san/episode/70",
        "myanimelist": 4935,
        "thetvdb": 7826815
    },
    {
        "season": 5,
        "episode": 19,
        "thetvdb url": "https://www.thetvdb.com/dereferrer/episode/7826817",
        "myanimelist url": "https://myanimelist.net/anime/4935/Ikkyuu-san/episode/71",
        "myanimelist": 4935,
        "thetvdb": 7826817
    },
    {
        "season": 5,
        "episode": 20,
        "thetvdb url": "https://www.thetvdb.com/dereferrer/episode/7826818",
        "myanimelist url": "https://myanimelist.net/anime/4935/Ikkyuu-san/episode/72",
        "myanimelist": 4935,
        "thetvdb": 7826818
    },
    {
        "season": 5,
        "episode": 21,
        "thetvdb url": "https://www.thetvdb.com/dereferrer/episode/7826819",
        "myanimelist url": "https://myanimelist.net/anime/4935/Ikkyuu-san/episode/73",
        "myanimelist": 4935,
        "thetvdb": 7826819
    },
    {
        "season": 5,
        "episode": 22,
        "thetvdb url": "https://www.thetvdb.com/dereferrer/episode/7826821",
        "myanimelist url": "https://myanimelist.net/anime/4935/Ikkyuu-san/episode/74",
        "myanimelist": 4935,
        "thetvdb": 7826821
    },
    {
        "season": 5,
        "episode": 23,
        "thetvdb url": "https://www.thetvdb.com/dereferrer/episode/7826822",
        "myanimelist url": "https://myanimelist.net/anime/4935/Ikkyuu-san/episode/75",
        "myanimelist": 4935,
        "thetvdb": 7826822
    },
    {
        "season": 5,
        "episode": 24,
        "thetvdb url": "https://www.thetvdb.com/dereferrer/episode/7826825",
        "myanimelist url": "https://myanimelist.net/anime/4935/Ikkyuu-san/episode/76",
        "myanimelist": 4935,
        "thetvdb": 7826825
    },
    {
        "season": 5,
        "episode": 25,
        "thetvdb url": "https://www.thetvdb.com/dereferrer/episode/7826826",
        "myanimelist url": "https://myanimelist.net/anime/4935/Ikkyuu-san/episode/77",
        "myanimelist": 4935,
        "thetvdb": 7826826
    },
    {
        "season": 5,
        "episode": 26,
        "thetvdb url": "https://www.thetvdb.com/dereferrer/episode/7826827",
        "myanimelist url": "https://myanimelist.net/anime/4935/Ikkyuu-san/episode/78",
        "myanimelist": 4935,
        "thetvdb": 7826827
    },
    {
        "season": 5,
        "episode": 27,
        "thetvdb url": "https://www.thetvdb.com/dereferrer/episode/7826828",
        "myanimelist url": "https://myanimelist.net/anime/4935/Ikkyuu-san/episode/79",
        "myanimelist": 4935,
        "thetvdb": 7826828
    },
    {
        "season": 5,
        "episode": 28,
        "thetvdb url": "https://www.thetvdb.com/dereferrer/episode/7826829",
        "myanimelist url": "https://myanimelist.net/anime/4935/Ikkyuu-san/episode/80",
        "myanimelist": 4935,
        "thetvdb": 7826829
    },
    {
        "season": 5,
        "episode": 29,
        "thetvdb url": "https://www.thetvdb.com/dereferrer/episode/7826830",
        "myanimelist url": "https://myanimelist.net/anime/4935/Ikkyuu-san/episode/81",
        "myanimelist": 4935,
        "thetvdb": 7826830
    },
    {
        "season": 5,
        "episode": 30,
        "thetvdb url": "https://www.thetvdb.com/dereferrer/episode/7826831",
        "myanimelist url": "https://myanimelist.net/anime/4935/Ikkyuu-san/episode/82",
        "myanimelist": 4935,
        "thetvdb": 7826831
    },
    {
        "season": 5,
        "episode": 31,
        "thetvdb url": "https://www.thetvdb.com/dereferrer/episode/7826832",
        "myanimelist url": "https://myanimelist.net/anime/4935/Ikkyuu-san/episode/83",
        "myanimelist": 4935,
        "thetvdb": 7826832
    },
    {
        "season": 5,
        "episode": 32,
        "thetvdb url": "https://www.thetvdb.com/dereferrer/episode/7826833",
        "myanimelist url": "https://myanimelist.net/anime/4935/Ikkyuu-san/episode/84",
        "myanimelist": 4935,
        "thetvdb": 7826833
    },
    {
        "season": 5,
        "episode": 33,
        "thetvdb url": "https://www.thetvdb.com/dereferrer/episode/7826834",
        "myanimelist url": "https://myanimelist.net/anime/4935/Ikkyuu-san/episode/85",
        "myanimelist": 4935,
        "thetvdb": 7826834
    },
    {
        "season": 5,
        "episode": 34,
        "thetvdb url": "https://www.thetvdb.com/dereferrer/episode/7826835",
        "myanimelist url": "https://myanimelist.net/anime/4935/Ikkyuu-san/episode/86",
        "myanimelist": 4935,
        "thetvdb": 7826835
    },
    {
        "season": 5,
        "episode": 35,
        "thetvdb url": "https://www.thetvdb.com/dereferrer/episode/7826836",
        "myanimelist url": "https://myanimelist.net/anime/4935/Ikkyuu-san/episode/87",
        "myanimelist": 4935,
        "thetvdb": 7826836
    },
    {
        "season": 5,
        "episode": 36,
        "thetvdb url": "https://www.thetvdb.com/dereferrer/episode/7826844",
        "myanimelist url": "https://myanimelist.net/anime/4935/Ikkyuu-san/episode/88",
        "myanimelist": 4935,
        "thetvdb": 7826844
    },
    {
        "season": 5,
        "episode": 37,
        "thetvdb url": "https://www.thetvdb.com/dereferrer/episode/7826845",
        "myanimelist url": "https://myanimelist.net/anime/4935/Ikkyuu-san/episode/89",
        "myanimelist": 4935,
        "thetvdb": 7826845
    },
    {
        "season": 5,
        "episode": 38,
        "thetvdb url": "https://www.thetvdb.com/dereferrer/episode/7826846",
        "myanimelist url": "https://myanimelist.net/anime/4935/Ikkyuu-san/episode/90",
        "myanimelist": 4935,
        "thetvdb": 7826846
    },
    {
        "season": 5,
        "episode": 39,
        "thetvdb url": "https://www.thetvdb.com/dereferrer/episode/7826847",
        "myanimelist url": "https://myanimelist.net/anime/4935/Ikkyuu-san/episode/91",
        "myanimelist": 4935,
        "thetvdb": 7826847
    },
    {
        "season": 5,
        "episode": 40,
        "thetvdb url": "https://www.thetvdb.com/dereferrer/episode/7826848",
        "myanimelist url": "https://myanimelist.net/anime/4935/Ikkyuu-san/episode/92",
        "myanimelist": 4935,
        "thetvdb": 7826848
    },
    {
        "season": 5,
        "episode": 41,
        "thetvdb url": "https://www.thetvdb.com/dereferrer/episode/7826849",
        "myanimelist url": "https://myanimelist.net/anime/4935/Ikkyuu-san/episode/93",
        "myanimelist": 4935,
        "thetvdb": 7826849
    },
    {
        "season": 5,
        "episode": 42,
        "thetvdb url": "https://www.thetvdb.com/dereferrer/episode/7826850",
        "myanimelist url": "https://myanimelist.net/anime/4935/Ikkyuu-san/episode/94",
        "myanimelist": 4935,
        "thetvdb": 7826850
    },
    {
        "season": 5,
        "episode": 43,
        "thetvdb url": "https://www.thetvdb.com/dereferrer/episode/7826851",
        "myanimelist url": "https://myanimelist.net/anime/4935/Ikkyuu-san/episode/95",
        "myanimelist": 4935,
        "thetvdb": 7826851
    },
    {
        "season": 5,
        "episode": 44,
        "thetvdb url": "https://www.thetvdb.com/dereferrer/episode/7826853",
        "myanimelist url": "https://myanimelist.net/anime/4935/Ikkyuu-san/episode/96",
        "myanimelist": 4935,
        "thetvdb": 7826853
    },
    {
        "season": 5,
        "episode": 45,
        "thetvdb url": "https://www.thetvdb.com/dereferrer/episode/7826854",
        "myanimelist url": "https://myanimelist.net/anime/4935/Ikkyuu-san/episode/97",
        "myanimelist": 4935,
        "thetvdb": 7826854
    },
    {
        "season": 5,
        "episode": 46,
        "thetvdb url": "https://www.thetvdb.com/dereferrer/episode/7826856",
        "myanimelist url": "https://myanimelist.net/anime/4935/Ikkyuu-san/episode/98",
        "myanimelist": 4935,
        "thetvdb": 7826856
    },
    {
        "season": 5,
        "episode": 47,
        "thetvdb url": "https://www.thetvdb.com/dereferrer/episode/7826857",
        "myanimelist url": "https://myanimelist.net/anime/4935/Ikkyuu-san/episode/99",
        "myanimelist": 4935,
        "thetvdb": 7826857
    },
    {
        "season": "6",
        "thetvdb url": "https://www.thetvdb.com/dereferrer/season/1853580",
        "myanimelist url": "https://myanimelist.net/anime/4935",
        "myanimelist": 4935,
        "thetvdb": 1853580
    },
    {
        "season": 6,
        "episode": 1,
        "thetvdb url": "https://www.thetvdb.com/dereferrer/episode/7826860",
        "myanimelist url": "https://myanimelist.net/anime/4935/Ikkyuu-san/episode/100",
        "myanimelist": 4935,
        "thetvdb": 7826860
    },
    {
        "season": 6,
        "episode": 2,
        "thetvdb url": "https://www.thetvdb.com/dereferrer/episode/7826862",
        "myanimelist url": "https://myanimelist.net/anime/4935/Ikkyuu-san/episode/101",
        "myanimelist": 4935,
        "thetvdb": 7826862
    },
    {
        "season": 6,
        "episode": 3,
        "thetvdb url": "https://www.thetvdb.com/dereferrer/episode/7826864",
        "myanimelist url": "https://myanimelist.net/anime/4935/Ikkyuu-san/episode/102",
        "myanimelist": 4935,
        "thetvdb": 7826864
    },
    {
        "season": 6,
        "episode": 4,
        "thetvdb url": "https://www.thetvdb.com/dereferrer/episode/7826866",
        "myanimelist url": "https://myanimelist.net/anime/4935/Ikkyuu-san/episode/103",
        "myanimelist": 4935,
        "thetvdb": 7826866
    },
    {
        "season": 6,
        "episode": 5,
        "thetvdb url": "https://www.thetvdb.com/dereferrer/episode/7826868",
        "myanimelist url": "https://myanimelist.net/anime/4935/Ikkyuu-san/episode/104",
        "myanimelist": 4935,
        "thetvdb": 7826868
    },
    {
        "season": 6,
        "episode": 6,
        "thetvdb url": "https://www.thetvdb.com/dereferrer/episode/7826870",
        "myanimelist url": "https://myanimelist.net/anime/4935/Ikkyuu-san/episode/105",
        "myanimelist": 4935,
        "thetvdb": 7826870
    },
    {
        "season": 6,
        "episode": 7,
        "thetvdb url": "https://www.thetvdb.com/dereferrer/episode/7826873",
        "myanimelist url": "https://myanimelist.net/anime/4935/Ikkyuu-san/episode/106",
        "myanimelist": 4935,
        "thetvdb": 7826873
    },
    {
        "season": 6,
        "episode": 8,
        "thetvdb url": "https://www.thetvdb.com/dereferrer/episode/7826874",
        "myanimelist url": "https://myanimelist.net/anime/4935/Ikkyuu-san/episode/107",
        "myanimelist": 4935,
        "thetvdb": 7826874
    },
    {
        "season": 6,
        "episode": 9,
        "thetvdb url": "https://www.thetvdb.com/dereferrer/episode/7826877",
        "myanimelist url": "https://myanimelist.net/anime/4935/Ikkyuu-san/episode/108",
        "myanimelist": 4935,
        "thetvdb": 7826877
    },
    {
        "season": 6,
        "episode": 10,
        "thetvdb url": "https://www.thetvdb.com/dereferrer/episode/7826879",
        "myanimelist url": "https://myanimelist.net/anime/4935/Ikkyuu-san/episode/109",
        "myanimelist": 4935,
        "thetvdb": 7826879
    },
    {
        "season": 6,
        "episode": 11,
        "thetvdb url": "https://www.thetvdb.com/dereferrer/episode/7826881",
        "myanimelist url": "https://myanimelist.net/anime/4935/Ikkyuu-san/episode/110",
        "myanimelist": 4935,
        "thetvdb": 7826881
    },
    {
        "season": 6,
        "episode": 12,
        "thetvdb url": "https://www.thetvdb.com/dereferrer/episode/7826882",
        "myanimelist url": "https://myanimelist.net/anime/4935/Ikkyuu-san/episode/111",
        "myanimelist": 4935,
        "thetvdb": 7826882
    },
    {
        "season": 6,
        "episode": 13,
        "thetvdb url": "https://www.thetvdb.com/dereferrer/episode/7826886",
        "myanimelist url": "https://myanimelist.net/anime/4935/Ikkyuu-san/episode/112",
        "myanimelist": 4935,
        "thetvdb": 7826886
    },
    {
        "season": 6,
        "episode": 14,
        "thetvdb url": "https://www.thetvdb.com/dereferrer/episode/7826888",
        "myanimelist url": "https://myanimelist.net/anime/4935/Ikkyuu-san/episode/113",
        "myanimelist": 4935,
        "thetvdb": 7826888
    },
    {
        "season": 6,
        "episode": 15,
        "thetvdb url": "https://www.thetvdb.com/dereferrer/episode/7826889",
        "myanimelist url": "https://myanimelist.net/anime/4935/Ikkyuu-san/episode/114",
        "myanimelist": 4935,
        "thetvdb": 7826889
    },
    {
        "season": 6,
        "episode": 16,
        "thetvdb url": "https://www.thetvdb.com/dereferrer/episode/7826890",
        "myanimelist url": "https://myanimelist.net/anime/4935/Ikkyuu-san/episode/115",
        "myanimelist": 4935,
        "thetvdb": 7826890
    },
    {
        "season": 6,
        "episode": 17,
        "thetvdb url": "https://www.thetvdb.com/dereferrer/episode/7826891",
        "myanimelist url": "https://myanimelist.net/anime/4935/Ikkyuu-san/episode/116",
        "myanimelist": 4935,
        "thetvdb": 7826891
    },
    {
        "season": 6,
        "episode": 18,
        "thetvdb url": "https://www.thetvdb.com/dereferrer/episode/7826892",
        "myanimelist url": "https://myanimelist.net/anime/4935/Ikkyuu-san/episode/117",
        "myanimelist": 4935,
        "thetvdb": 7826892
    },
    {
        "season": 6,
        "episode": 19,
        "thetvdb url": "https://www.thetvdb.com/dereferrer/episode/7826893",
        "myanimelist url": "https://myanimelist.net/anime/4935/Ikkyuu-san/episode/118",
        "myanimelist": 4935,
        "thetvdb": 7826893
    },
    {
        "season": 6,
        "episode": 20,
        "thetvdb url": "https://www.thetvdb.com/dereferrer/episode/7826894",
        "myanimelist url": "https://myanimelist.net/anime/4935/Ikkyuu-san/episode/119",
        "myanimelist": 4935,
        "thetvdb": 7826894
    },
    {
        "season": 6,
        "episode": 21,
        "thetvdb url": "https://www.thetvdb.com/dereferrer/episode/7826895",
        "myanimelist url": "https://myanimelist.net/anime/4935/Ikkyuu-san/episode/120",
        "myanimelist": 4935,
        "thetvdb": 7826895
    },
    {
        "season": 6,
        "episode": 22,
        "thetvdb url": "https://www.thetvdb.com/dereferrer/episode/7826896",
        "myanimelist url": "https://myanimelist.net/anime/4935/Ikkyuu-san/episode/121",
        "myanimelist": 4935,
        "thetvdb": 7826896
    },
    {
        "season": 6,
        "episode": 23,
        "thetvdb url": "https://www.thetvdb.com/dereferrer/episode/7826897",
        "myanimelist url": "https://myanimelist.net/anime/4935/Ikkyuu-san/episode/122",
        "myanimelist": 4935,
        "thetvdb": 7826897
    },
    {
        "season": 6,
        "episode": 24,
        "thetvdb url": "https://www.thetvdb.com/dereferrer/episode/7826898",
        "myanimelist url": "https://myanimelist.net/anime/4935/Ikkyuu-san/episode/123",
        "myanimelist": 4935,
        "thetvdb": 7826898
    },
    {
        "season": 6,
        "episode": 25,
        "thetvdb url": "https://www.thetvdb.com/dereferrer/episode/7826899",
        "myanimelist url": "https://myanimelist.net/anime/4935/Ikkyuu-san/episode/124",
        "myanimelist": 4935,
        "thetvdb": 7826899
    },
    {
        "season": 6,
        "episode": 26,
        "thetvdb url": "https://www.thetvdb.com/dereferrer/episode/7826900",
        "myanimelist url": "https://myanimelist.net/anime/4935/Ikkyuu-san/episode/125",
        "myanimelist": 4935,
        "thetvdb": 7826900
    },
    {
        "season": 6,
        "episode": 27,
        "thetvdb url": "https://www.thetvdb.com/dereferrer/episode/7826901",
        "myanimelist url": "https://myanimelist.net/anime/4935/Ikkyuu-san/episode/126",
        "myanimelist": 4935,
        "thetvdb": 7826901
    },
    {
        "season": 6,
        "episode": 28,
        "thetvdb url": "https://www.thetvdb.com/dereferrer/episode/7826903",
        "myanimelist url": "https://myanimelist.net/anime/4935/Ikkyuu-san/episode/127",
        "myanimelist": 4935,
        "thetvdb": 7826903
    },
    {
        "season": 6,
        "episode": 29,
        "thetvdb url": "https://www.thetvdb.com/dereferrer/episode/7826904",
        "myanimelist url": "https://myanimelist.net/anime/4935/Ikkyuu-san/episode/128",
        "myanimelist": 4935,
        "thetvdb": 7826904
    },
    {
        "season": 6,
        "episode": 30,
        "thetvdb url": "https://www.thetvdb.com/dereferrer/episode/7826905",
        "myanimelist url": "https://myanimelist.net/anime/4935/Ikkyuu-san/episode/129",
        "myanimelist": 4935,
        "thetvdb": 7826905
    },
    {
        "season": 6,
        "episode": 31,
        "thetvdb url": "https://www.thetvdb.com/dereferrer/episode/7826908",
        "myanimelist url": "https://myanimelist.net/anime/4935/Ikkyuu-san/episode/130",
        "myanimelist": 4935,
        "thetvdb": 7826908
    },
    {
        "season": 6,
        "episode": 32,
        "thetvdb url": "https://www.thetvdb.com/dereferrer/episode/7826910",
        "myanimelist url": "https://myanimelist.net/anime/4935/Ikkyuu-san/episode/131",
        "myanimelist": 4935,
        "thetvdb": 7826910
    },
    {
        "season": 6,
        "episode": 33,
        "thetvdb url": "https://www.thetvdb.com/dereferrer/episode/7826917",
        "myanimelist url": "https://myanimelist.net/anime/4935/Ikkyuu-san/episode/132",
        "myanimelist": 4935,
        "thetvdb": 7826917
    },
    {
        "season": 6,
        "episode": 34,
        "thetvdb url": "https://www.thetvdb.com/dereferrer/episode/7826919",
        "myanimelist url": "https://myanimelist.net/anime/4935/Ikkyuu-san/episode/133",
        "myanimelist": 4935,
        "thetvdb": 7826919
    },
    {
        "season": 6,
        "episode": 35,
        "thetvdb url": "https://www.thetvdb.com/dereferrer/episode/7826920",
        "myanimelist url": "https://myanimelist.net/anime/4935/Ikkyuu-san/episode/134",
        "myanimelist": 4935,
        "thetvdb": 7826920
    },
    {
        "season": 6,
        "episode": 36,
        "thetvdb url": "https://www.thetvdb.com/dereferrer/episode/7826922",
        "myanimelist url": "https://myanimelist.net/anime/4935/Ikkyuu-san/episode/135",
        "myanimelist": 4935,
        "thetvdb": 7826922
    },
    {
        "season": 6,
        "episode": 37,
        "thetvdb url": "https://www.thetvdb.com/dereferrer/episode/7826923",
        "myanimelist url": "https://myanimelist.net/anime/4935/Ikkyuu-san/episode/136",
        "myanimelist": 4935,
        "thetvdb": 7826923
    },
    {
        "season": 6,
        "episode": 38,
        "thetvdb url": "https://www.thetvdb.com/dereferrer/episode/7826924",
        "myanimelist url": "https://myanimelist.net/anime/4935/Ikkyuu-san/episode/137",
        "myanimelist": 4935,
        "thetvdb": 7826924
    },
    {
        "season": 6,
        "episode": 39,
        "thetvdb url": "https://www.thetvdb.com/dereferrer/episode/7826925",
        "myanimelist url": "https://myanimelist.net/anime/4935/Ikkyuu-san/episode/138",
        "myanimelist": 4935,
        "thetvdb": 7826925
    },
    {
        "season": 6,
        "episode": 40,
        "thetvdb url": "https://www.thetvdb.com/dereferrer/episode/7826926",
        "myanimelist url": "https://myanimelist.net/anime/4935/Ikkyuu-san/episode/139",
        "myanimelist": 4935,
        "thetvdb": 7826926
    },
    {
        "season": 6,
        "episode": 41,
        "thetvdb url": "https://www.thetvdb.com/dereferrer/episode/7826927",
        "myanimelist url": "https://myanimelist.net/anime/4935/Ikkyuu-san/episode/140",
        "myanimelist": 4935,
        "thetvdb": 7826927
    },
    {
        "season": 6,
        "episode": 42,
        "thetvdb url": "https://www.thetvdb.com/dereferrer/episode/7826929",
        "myanimelist url": "https://myanimelist.net/anime/4935/Ikkyuu-san/episode/141",
        "myanimelist": 4935,
        "thetvdb": 7826929
    },
    {
        "season": 6,
        "episode": 43,
        "thetvdb url": "https://www.thetvdb.com/dereferrer/episode/7826930",
        "myanimelist url": "https://myanimelist.net/anime/4935/Ikkyuu-san/episode/142",
        "myanimelist": 4935,
        "thetvdb": 7826930
    },
    {
        "season": 6,
        "episode": 44,
        "thetvdb url": "https://www.thetvdb.com/dereferrer/episode/7826931",
        "myanimelist url": "https://myanimelist.net/anime/4935/Ikkyuu-san/episode/143",
        "myanimelist": 4935,
        "thetvdb": 7826931
    },
    {
        "season": 6,
        "episode": 45,
        "thetvdb url": "https://www.thetvdb.com/dereferrer/episode/7826932",
        "myanimelist url": "https://myanimelist.net/anime/4935/Ikkyuu-san/episode/144",
        "myanimelist": 4935,
        "thetvdb": 7826932
    },
    {
        "season": 6,
        "episode": 46,
        "thetvdb url": "https://www.thetvdb.com/dereferrer/episode/7826933",
        "myanimelist url": "https://myanimelist.net/anime/4935/Ikkyuu-san/episode/145",
        "myanimelist": 4935,
        "thetvdb": 7826933
    },
    {
        "season": 6,
        "episode": 47,
        "thetvdb url": "https://www.thetvdb.com/dereferrer/episode/7826935",
        "myanimelist url": "https://myanimelist.net/anime/4935/Ikkyuu-san/episode/146",
        "myanimelist": 4935,
        "thetvdb": 7826935
    },
    {
        "season": "7",
        "thetvdb url": "https://www.thetvdb.com/dereferrer/season/1853581",
        "myanimelist url": "https://myanimelist.net/anime/4935",
        "myanimelist": 4935,
        "thetvdb": 1853581
    },
    {
        "season": 7,
        "episode": 1,
        "thetvdb url": "https://www.thetvdb.com/dereferrer/episode/7826936",
        "myanimelist url": "https://myanimelist.net/anime/4935/Ikkyuu-san/episode/147",
        "myanimelist": 4935,
        "thetvdb": 7826936
    },
    {
        "season": 7,
        "episode": 2,
        "thetvdb url": "https://www.thetvdb.com/dereferrer/episode/7826939",
        "myanimelist url": "https://myanimelist.net/anime/4935/Ikkyuu-san/episode/148",
        "myanimelist": 4935,
        "thetvdb": 7826939
    },
    {
        "season": 7,
        "episode": 3,
        "thetvdb url": "https://www.thetvdb.com/dereferrer/episode/7826940",
        "myanimelist url": "https://myanimelist.net/anime/4935/Ikkyuu-san/episode/149",
        "myanimelist": 4935,
        "thetvdb": 7826940
    },
    {
        "season": 7,
        "episode": 4,
        "thetvdb url": "https://www.thetvdb.com/dereferrer/episode/7826941",
        "myanimelist url": "https://myanimelist.net/anime/4935/Ikkyuu-san/episode/150",
        "myanimelist": 4935,
        "thetvdb": 7826941
    },
    {
        "season": 7,
        "episode": 5,
        "thetvdb url": "https://www.thetvdb.com/dereferrer/episode/7828548",
        "myanimelist url": "https://myanimelist.net/anime/4935/Ikkyuu-san/episode/151",
        "myanimelist": 4935,
        "thetvdb": 7828548
    },
    {
        "season": 7,
        "episode": 6,
        "thetvdb url": "https://www.thetvdb.com/dereferrer/episode/7828565",
        "myanimelist url": "https://myanimelist.net/anime/4935/Ikkyuu-san/episode/152",
        "myanimelist": 4935,
        "thetvdb": 7828565
    },
    {
        "season": 7,
        "episode": 7,
        "thetvdb url": "https://www.thetvdb.com/dereferrer/episode/7828575",
        "myanimelist url": "https://myanimelist.net/anime/4935/Ikkyuu-san/episode/153",
        "myanimelist": 4935,
        "thetvdb": 7828575
    },
    {
        "season": 7,
        "episode": 8,
        "thetvdb url": "https://www.thetvdb.com/dereferrer/episode/7828580",
        "myanimelist url": "https://myanimelist.net/anime/4935/Ikkyuu-san/episode/154",
        "myanimelist": 4935,
        "thetvdb": 7828580
    },
    {
        "season": 7,
        "episode": 9,
        "thetvdb url": "https://www.thetvdb.com/dereferrer/episode/7828601",
        "myanimelist url": "https://myanimelist.net/anime/4935/Ikkyuu-san/episode/155",
        "myanimelist": 4935,
        "thetvdb": 7828601
    },
    {
        "season": 7,
        "episode": 10,
        "thetvdb url": "https://www.thetvdb.com/dereferrer/episode/7828609",
        "myanimelist url": "https://myanimelist.net/anime/4935/Ikkyuu-san/episode/156",
        "myanimelist": 4935,
        "thetvdb": 7828609
    },
    {
        "season": 7,
        "episode": 11,
        "thetvdb url": "https://www.thetvdb.com/dereferrer/episode/7828614",
        "myanimelist url": "https://myanimelist.net/anime/4935/Ikkyuu-san/episode/157",
        "myanimelist": 4935,
        "thetvdb": 7828614
    }
]